{"name":"GET - Get all order without login","id":"order;get---get-all-order-without-login","testSteps":[{"number":1,"description":"Given I set GET api endpoints order","duration":3,"startTime":"2023-05-10T21:57:49.859885800+07:00[Asia/Jakarta]","result":"SUCCESS","precondition":false,"level":0},{"number":2,"description":"When I send GET HTTP request order2","duration":214,"startTime":"2023-05-10T21:57:49.864883900+07:00[Asia/Jakarta]","result":"SUCCESS","precondition":false,"level":0,"children":[{"number":3,"description":"GET https://altashop-api.fly.dev/api/orders","duration":0,"startTime":"2023-05-10T21:57:50.077762400+07:00[Asia/Jakarta]","result":"SUCCESS","restQuery":{"method":"GET","path":"https://altashop-api.fly.dev/api/orders","content":"","contentType":"null","requestHeaders":"Accept\u003d*/*","requestCookies":"","responseHeaders":"content-type: application/json\r\ndate: Wed, 10 May 2023 14:57:49 GMT\r\ncontent-encoding: gzip\r\ntransfer-encoding: chunked\r\nserver: Fly/3f2597ca (2023-05-03)\r\nvia: 1.1 fly.io\r\nfly-request-id: 01H032P7S8F4ZR9WWPSF0B0GWQ-sin\r","responseCookies":"\r","responseBody":"{\n    \"error\": \"unauthorized\"\n}","statusCode":401},"precondition":false,"level":1}]},{"number":4,"description":"Then I receive valid HTTP response code 401 order","duration":2,"startTime":"2023-05-10T21:57:50.080762600+07:00[Asia/Jakarta]","result":"SUCCESS","precondition":false,"level":0}],"userStory":{"id":"order","storyName":"Order","displayName":"Order","path":"6.%20Order.feature","narrative":"  As a user\n  I want to order something\n  So that I can order item that I want","type":"feature","qualifiedTag":{"name":"Order","type":"feature","displayName":"Order"}},"featureTag":{"name":"Order","type":"feature","displayName":"Order"},"title":"GET - Get all order without login","description":"","tags":[{"name":"Windows","type":"context","displayName":"Windows"},{"name":"Order","type":"feature","displayName":"Order"}],"allTags":[{"name":"Windows","type":"context","displayName":"Windows"},{"name":"Order","type":"feature","displayName":"Order"}],"startTime":"2023-05-10T21:57:49.854889+07:00[Asia/Jakarta]","duration":229,"projectKey":"","isManualTestingUpToDate":false,"context":"windows","manual":false,"testSource":"Cucumber","result":"SUCCESS"}